satori_serpentarium-0.0.2a4.dist-info/METADATA
satori_serpentarium-0.0.2a4.dist-info/RECORD
satori_serpentarium-0.0.2a4.dist-info/WHEEL
satori_serpentarium-0.0.2a4.dist-info/top_level.txt
serpentarium/__init__.py
serpentarium/__main__.py
serpentarium/config.yml
serpentarium/engine/CompositionNode.py
serpentarium/engine/ExecutionContext.py
serpentarium/engine/Mod.py
serpentarium/engine/ModContext.py
serpentarium/engine/Runner.py
serpentarium/engine/__init__.py
serpentarium/logging/LoggingFormatter.py
serpentarium/logging/LoggingUtil.py
serpentarium/logging/RtmLoggingHandler.py
serpentarium/logging/__init__.py
serpentarium/mods/Greeter.py
serpentarium/mods/RtmPublisher.py
serpentarium/mods/RtmSubscriber.py
serpentarium/mods/__init__.py
serpentarium/monitoring/AvgMetric.py
serpentarium/monitoring/CompoundMonitor.py
serpentarium/monitoring/DatadogMonitor.py
serpentarium/monitoring/HeartbeatMetric.py
serpentarium/monitoring/IncrementalMetric.py
serpentarium/monitoring/Metric.py
serpentarium/monitoring/Monitor.py
serpentarium/monitoring/RtmMonitor.py
serpentarium/monitoring/__init__.py
serpentarium/rtm/RtmClientUtil.py
serpentarium/rtm/__init__.py
serpentarium/util/__init__.py
serpentarium/util/helpers.py
