Metadata-Version: 2.1
Name: satori-serpentarium
Version: 0.0.2a4
Summary: Satori composer for Python
Home-page: https://bitbucket.addsrv.com/users/yzhuk/repos/serpentarium/browse
License: UNKNOWN
Platform: UNKNOWN
Requires-Python: >=3.6.5
Requires-Dist: datadog
Requires-Dist: networkx
Requires-Dist: wsaccel
Requires-Dist: PyYAML
Requires-Dist: retrying
Requires-Dist: pydot
Requires-Dist: graphviz
Requires-Dist: argparse
Requires-Dist: satori-rtm-sdk
